marqeta_diva_mcp/__init__.py
marqeta_diva_mcp/__main__.py
marqeta_diva_mcp/client.py
marqeta_diva_mcp/embeddings.py
marqeta_diva_mcp/local_storage.py
marqeta_diva_mcp/rag_tools.py
marqeta_diva_mcp/server.py
marqeta_diva_mcp/vector_store.py
marqeta_diva_mcp-0.3.0.dist-info/METADATA
marqeta_diva_mcp-0.3.0.dist-info/WHEEL
marqeta_diva_mcp-0.3.0.dist-info/entry_points.txt
marqeta_diva_mcp-0.3.0.dist-info/licenses/LICENSE
marqeta_diva_mcp-0.3.0.dist-info/RECORD
