Metadata-Version: 2.4
Name: marqeta-diva-mcp
Version: 0.3.0
Summary: MCP server for Marqeta DiVA API - Data insights, Visualization, and Analytics
Project-URL: Homepage, https://github.com/zvika-finally/marqeta-diva-mcp
Project-URL: Repository, https://github.com/zvika-finally/marqeta-diva-mcp
Project-URL: Issues, https://github.com/zvika-finally/marqeta-diva-mcp/issues
Project-URL: Documentation, https://github.com/zvika-finally/marqeta-diva-mcp#readme
Author-email: Zvika Badalov <zvika.badalov@finally.com>
License: MIT
License-File: LICENSE
Keywords: analytics,api,diva,fintech,marqeta,mcp,model-context-protocol
Classifier: Development Status :: 4 - Beta
Classifier: Intended Audience :: Developers
Classifier: License :: OSI Approved :: MIT License
Classifier: Programming Language :: Python :: 3
Classifier: Programming Language :: Python :: 3.10
Classifier: Programming Language :: Python :: 3.11
Classifier: Programming Language :: Python :: 3.12
Classifier: Topic :: Office/Business :: Financial
Classifier: Topic :: Software Development :: Libraries :: Python Modules
Requires-Python: >=3.10
Requires-Dist: httpx>=0.27.0
Requires-Dist: mcp>=1.0.0
Requires-Dist: pydantic>=2.0.0
Requires-Dist: python-dotenv>=1.0.0
Provides-Extra: all
Requires-Dist: black>=23.0.0; extra == 'all'
Requires-Dist: chromadb>=0.4.22; extra == 'all'
Requires-Dist: pytest>=7.0.0; extra == 'all'
Requires-Dist: ruff>=0.1.0; extra == 'all'
Requires-Dist: sentence-transformers>=2.3.1; extra == 'all'
Provides-Extra: dev
Requires-Dist: black>=23.0.0; extra == 'dev'
Requires-Dist: pytest>=7.0.0; extra == 'dev'
Requires-Dist: ruff>=0.1.0; extra == 'dev'
Provides-Extra: rag
Requires-Dist: chromadb>=0.4.22; extra == 'rag'
Requires-Dist: sentence-transformers>=2.3.1; extra == 'rag'
